{"assets":{"3559C8E587DE6FF7C6AFC2433E257C5B":{"type":"texture","index":7,"assetRequest":{"type":"slide","state":"contents","slide":"none"},"url":{"native":"assets/E660E24F-C165-47BD-A5CC-98BC2FC0611B.pdf"},"width":638,"height":21},"58084A932F98F87AD2CD2D550BB8C3C2":{"type":"texture","index":12,"assetRequest":{"type":"slide","state":"contents","slide":"none"},"url":{"native":"assets/E660E24F-C165-47BD-A5CC-98BC2FC0611B.pdf"},"width":750,"height":143},"09765695C6431BB50006402D4727B402":{"type":"texture","index":3,"assetRequest":{"type":"slide","state":"contents","slide":"none"},"url":{"native":"assets/E660E24F-C165-47BD-A5CC-98BC2FC0611B.pdf"},"width":14,"height":20},"372D79640346414F225CBCC917480A6A":{"type":"texture","index":5,"assetRequest":{"type":"slide","state":"contents","slide":"none"},"url":{"native":"assets/E660E24F-C165-47BD-A5CC-98BC2FC0611B.pdf"},"width":788,"height":179},"C7A3C9712269BCFBA377590A13996216":{"type":"texture","index":0,"assetRequest":{"type":"slide","state":"contents","slide":"none"},"url":{"native":"assets/E660E24F-C165-47BD-A5CC-98BC2FC0611B.pdf"},"width":1024,"height":768},"2DA405A25AE2480223DCDBABEFBFEF7B":{"type":"texture","index":4,"assetRequest":{"type":"slide","state":"contents","slide":"none"},"url":{"native":"assets/E660E24F-C165-47BD-A5CC-98BC2FC0611B.pdf"},"width":342,"height":114},"E61C829B516BE9C2D3380EFB12DD58F5":{"type":"texture","index":6,"assetRequest":{"type":"slide","state":"contents","slide":"none"},"url":{"native":"assets/E660E24F-C165-47BD-A5CC-98BC2FC0611B.pdf"},"width":652,"height":21},"43059EB58D01D0B6F8BAC866913D3768":{"type":"texture","index":10,"assetRequest":{"type":"slide","state":"contents","slide":"none"},"url":{"native":"assets/E660E24F-C165-47BD-A5CC-98BC2FC0611B.pdf"},"width":750,"height":144},"0481037350EC986D0C7472F6F4EA3FCB":{"type":"texture","index":8,"assetRequest":{"type":"slide","state":"contents","slide":"none"},"url":{"native":"assets/E660E24F-C165-47BD-A5CC-98BC2FC0611B.pdf"},"width":550,"height":21},"F6813DEC34DB90071FC3F14E41C3E19E":{"type":"texture","index":9,"assetRequest":{"type":"slide","state":"contents","slide":"none"},"url":{"native":"assets/E660E24F-C165-47BD-A5CC-98BC2FC0611B.pdf"},"width":285,"height":21},"1834EDE3D908F36093AD2909D975FA4C":{"type":"texture","index":2,"assetRequest":{"type":"slide","state":"contents","slide":"none"},"url":{"native":"assets/E660E24F-C165-47BD-A5CC-98BC2FC0611B.pdf"},"width":43,"height":43},"AB228C89596CE7DDB6A7B57EC4805A00":{"type":"texture","index":11,"assetRequest":{"type":"slide","state":"contents","slide":"none"},"url":{"native":"assets/E660E24F-C165-47BD-A5CC-98BC2FC0611B.pdf"},"width":13,"height":19},"05EBB03D9A851B3084D14365D8904CA2":{"type":"texture","index":1,"assetRequest":{"type":"slide","state":"contents","slide":"none"},"url":{"native":"assets/E660E24F-C165-47BD-A5CC-98BC2FC0611B.pdf"},"width":76,"height":65}},"events":[{"effects":[{"beginTime":0,"baseLayer":{"animations":[],"initialState":{"affineTransform":[1,0,0,1,0,0],"masksToBounds":false,"rotation":0,"scale":1,"position":{"pointX":512,"pointY":384},"width":1024,"sublayerTransform":[1,0,0,0,0,1,0,0,0,0,1,0,0,0,0,1],"contentsRect":{"y":0,"x":0,"width":1,"height":1},"opacity":1,"edgeAntialiasingMask":251658240,"height":768,"hidden":false,"anchorPoint":{"pointX":0.5,"pointY":0.5}},"objectID":"0","layers":[{"animations":[],"initialState":{"affineTransform":[1,0,0,1,0,0],"masksToBounds":false,"rotation":0,"scale":1,"position":{"pointX":512,"pointY":384},"width":1024,"sublayerTransform":[1,0,0,0,0,1,0,0,0,0,1,-0.0004922987690640373,0,0,0,1],"contentsRect":{"y":0,"x":0,"width":1,"height":1},"opacity":1,"edgeAntialiasingMask":251658240,"height":768,"hidden":false,"anchorPoint":{"pointX":0.5,"pointY":0.5}},"layers":[{"animations":[{"timeOffset":0,"beginTime":0,"repeatCount":0,"animations":[{"timeOffset":0,"from":{"scalar":0},"beginTime":0,"repeatCount":0,"fillMode":"both","duration":1,"autoreverses":false,"timingFunction":"EaseInEaseOut","property":"zPosition","to":{"scalar":0}}],"fillMode":"both","autoreverses":false,"duration":1}],"initialState":{"affineTransform":[1,0,0,1,0,0],"masksToBounds":false,"rotation":0,"scale":1,"position":{"pointX":512,"pointY":384},"width":1024,"sublayerTransform":[1,0,0,0,0,1,0,0,0,0,1,0,0,0,0,1],"contentsRect":{"y":0,"x":0,"width":1,"height":1},"opacity":1,"edgeAntialiasingMask":251658240,"height":768,"hidden":false,"anchorPoint":{"pointX":0.5,"pointY":0.5}},"layers":[{"animations":[],"layers":[],"texturedRectangle":{"isBackgroundTexture":true,"singleTextureOpacity":1,"textureType":1,"textBaseline":0,"textXHeight":0,"isVerticalText":false},"initialState":{"affineTransform":[1,0,0,1,0,0],"masksToBounds":false,"rotation":0,"scale":1,"position":{"pointX":512,"pointY":384},"width":1024,"sublayerTransform":[1,0,0,0,0,1,0,0,0,0,1,0,0,0,0,1],"contentsRect":{"y":0,"x":0,"width":1,"height":1},"opacity":1,"edgeAntialiasingMask":0,"height":768,"hidden":false,"anchorPoint":{"pointX":0.5,"pointY":0.5}},"texture":"C7A3C9712269BCFBA377590A13996216"}]}]},{"animations":[{"timeOffset":0,"beginTime":0,"repeatCount":0,"animations":[{"timeOffset":0,"from":{"scalar":0.001},"beginTime":0,"repeatCount":0,"fillMode":"both","duration":1,"autoreverses":false,"timingFunction":"EaseInEaseOut","property":"zPosition","to":{"scalar":0.001}}],"fillMode":"both","autoreverses":false,"duration":1}],"initialState":{"affineTransform":[1,0,0,1,0,0],"masksToBounds":false,"rotation":0,"scale":1,"position":{"pointX":986.1420440673828,"pointY":735.210319519043},"width":73.28860473632812,"sublayerTransform":[1,0,0,0,0,1,0,0,0,0,1,0,0,0,0,1],"contentsRect":{"y":0,"x":0,"width":1,"height":1},"opacity":1,"edgeAntialiasingMask":251658240,"height":61.73155212402344,"hidden":false,"anchorPoint":{"pointX":0.5,"pointY":0.5}},"layers":[{"animations":[],"layers":[],"texturedRectangle":{"isBackgroundTexture":true,"singleTextureOpacity":1,"textureType":5,"textBaseline":0,"textXHeight":0,"isVerticalText":false},"initialState":{"affineTransform":[1,0,0,1,0,0],"masksToBounds":false,"rotation":0,"scale":1,"position":{"pointX":36.64430236816407,"pointY":30.86577606201172},"width":76,"sublayerTransform":[1,0,0,0,0,1,0,0,0,0,1,0,0,0,0,1],"contentsRect":{"y":0,"x":0,"width":1,"height":1},"opacity":1,"edgeAntialiasingMask":0,"height":65,"hidden":false,"anchorPoint":{"pointX":0.501869000886616,"pointY":0.4955433772160457}},"texture":"05EBB03D9A851B3084D14365D8904CA2"}]},{"animations":[{"timeOffset":0,"beginTime":0,"repeatCount":0,"animations":[{"timeOffset":0,"from":{"scalar":0.002},"beginTime":0,"repeatCount":0,"fillMode":"both","duration":1,"autoreverses":false,"timingFunction":"EaseInEaseOut","property":"zPosition","to":{"scalar":0.002}}],"fillMode":"both","autoreverses":false,"duration":1}],"initialState":{"affineTransform":[1,0,0,1,0,0],"masksToBounds":false,"rotation":0,"scale":1,"position":{"pointX":986.1420244574547,"pointY":735.2103114724159},"width":29.87999618053436,"sublayerTransform":[1,0,0,0,0,1,0,0,0,0,1,0,0,0,0,1],"contentsRect":{"y":0,"x":0,"width":1,"height":1},"opacity":1,"edgeAntialiasingMask":251658240,"height":30.39999306201935,"hidden":false,"anchorPoint":{"pointX":0.5,"pointY":0.5}},"layers":[{"animations":[],"layers":[],"texturedRectangle":{"singleTextureOpacity":1,"textXHeight":0,"shapePath":{"lineWidth":1,"flatness":0.6,"lineCapStyle":0,"elements":[{"type":"MoveToPoint","points":[[31.70619841529719,10.46229085407344]]},{"type":"AddCurve","points":[[37.54063059186342,16.3982587376297],[37.54063059186342,26.02236420720214],[31.70619841529719,31.9583320907584]]},{"type":"AddCurve","points":[[25.87176623873097,37.89429997431466],[16.41228267617839,37.89429997431466],[10.57785049961217,31.9583320907584]]},{"type":"AddCurve","points":[[4.743418323045944,26.02236420720214],[4.743418323045944,16.3982587376297],[10.57785049961217,10.46229085407344]]},{"type":"AddCurve","points":[[16.41228267617839,4.526322970517185],[25.87176623873097,4.526322970517185],[31.70619841529719,10.46229085407344]]},{"type":"CloseSubpath"},{"type":"MoveToPoint","points":[[31.70619841529719,10.46229085407344]]}],"windingRule":0,"lineJoinStyle":0,"miterLimit":10},"isBackgroundTexture":true,"textBaseline":0,"isVerticalText":false,"textureType":5},"initialState":{"affineTransform":[1,0,0,1,0,0],"masksToBounds":false,"rotation":0,"scale":1,"position":{"pointX":14.93999862670898,"pointY":15.19999694824219},"width":43,"sublayerTransform":[1,0,0,0,0,1,0,0,0,0,1,0,0,0,0,1],"contentsRect":{"y":0,"x":0,"width":1,"height":1},"opacity":1,"edgeAntialiasingMask":0,"height":43,"hidden":false,"anchorPoint":{"pointX":0.4916749998580578,"pointY":0.4932630672011264}},"texture":"1834EDE3D908F36093AD2909D975FA4C"}]},{"animations":[{"timeOffset":0,"beginTime":0,"repeatCount":0,"animations":[{"timeOffset":0,"from":{"scalar":0.003},"beginTime":0,"repeatCount":0,"fillMode":"both","duration":1,"autoreverses":false,"timingFunction":"EaseInEaseOut","property":"zPosition","to":{"scalar":0.003}}],"fillMode":"both","autoreverses":false,"duration":1}],"initialState":{"affineTransform":[1,0,0,1,0,0],"masksToBounds":false,"rotation":0,"scale":1,"position":{"pointX":986.1420288085938,"pointY":735.2103118896484},"width":19.43999975919724,"sublayerTransform":[1,0,0,0,0,1,0,0,0,0,1,0,0,0,0,1],"contentsRect":{"y":0,"x":0,"width":1,"height":1},"opacity":1,"edgeAntialiasingMask":251658240,"height":26.39999389648438,"hidden":false,"anchorPoint":{"pointX":0.5,"pointY":0.5}},"layers":[{"animations":[{"timeOffset":0,"beginTime":0,"repeatCount":0,"animations":[{"timeOffset":0,"from":{"scalar":1},"beginTime":0,"repeatCount":0,"fillMode":"both","duration":1,"autoreverses":false,"timingFunction":"EaseInEaseOut","property":"transform.scale.x","to":{"scalar":0.9285714285714286}},{"timeOffset":0,"from":{"scalar":1},"beginTime":0,"repeatCount":0,"fillMode":"both","duration":1,"autoreverses":false,"timingFunction":"EaseInEaseOut","property":"transform.scale.y","to":{"scalar":0.95}},{"timeOffset":0,"from":{"texture":"09765695C6431BB50006402D4727B402"},"beginTime":0,"repeatCount":0,"fillMode":"both","duration":1,"autoreverses":false,"timingFunction":"EaseInEaseOut","property":"contents","to":{"texture":"AB228C89596CE7DDB6A7B57EC4805A00"}},{"timeOffset":0,"from":{"pointX":0,"pointY":0},"beginTime":0,"repeatCount":0,"fillMode":"both","duration":1,"autoreverses":false,"timingFunction":"EaseInEaseOut","property":"transform.translation","to":{"pointX":-0.510144923499638,"pointY":0.4894844353199233}}],"fillMode":"both","autoreverses":false,"duration":1}],"layers":[],"texturedRectangle":{"singleTextureOpacity":1,"textXHeight":0.5931,"textBaseline":0.8382151141762734,"isBackgroundTexture":true,"isVerticalText":false,"textColor":[0.8983241319656372,0.8015710711479187,0.4699850678443909,1],"textureType":6},"initialState":{"affineTransform":[1,0,0,1,0,0],"masksToBounds":false,"rotation":0,"scale":1,"position":{"pointX":9.720000000000027,"pointY":13.19999635219574},"width":14,"sublayerTransform":[1,0,0,0,0,1,0,0,0,0,1,0,0,0,0,1],"contentsRect":{"y":0,"x":0,"width":1,"height":1},"opacity":1,"edgeAntialiasingMask":0,"height":20,"hidden":false,"anchorPoint":{"pointX":0.5101449234996542,"pointY":0.5105155646800995}},"texture":"09765695C6431BB50006402D4727B402"}]},{"animations":[{"timeOffset":0,"beginTime":0,"repeatCount":0,"animations":[{"timeOffset":0,"from":{"scalar":0.004},"beginTime":0,"repeatCount":0,"fillMode":"both","duration":1,"autoreverses":false,"timingFunction":"EaseInEaseOut","property":"zPosition","to":{"scalar":0.004}}],"fillMode":"both","autoreverses":false,"duration":1}],"initialState":{"affineTransform":[1,0,0,1,0,0],"masksToBounds":false,"rotation":0,"scale":1,"position":{"pointX":511.9999904632568,"pointY":383.9999988079071},"width":338.7513236999512,"sublayerTransform":[1,0,0,0,0,1,0,0,0,0,1,0,0,0,0,1],"contentsRect":{"y":0,"x":0,"width":1,"height":1},"opacity":1,"edgeAntialiasingMask":251658240,"height":110.2344946861267,"hidden":false,"anchorPoint":{"pointX":0.5,"pointY":0.5}},"layers":[{"animations":[{"timeOffset":0,"beginTime":0,"repeatCount":0,"animations":[{"timeOffset":0,"from":{"texture":"2DA405A25AE2480223DCDBABEFBFEF7B"},"beginTime":0,"repeatCount":0,"fillMode":"both","duration":1,"autoreverses":false,"timingFunction":"EaseInEaseOut","property":"contents","to":{"texture":"2DA405A25AE2480223DCDBABEFBFEF7B"}},{"timeOffset":0,"from":{"scalar":-5.271816814553125e-10},"beginTime":0,"repeatCount":0,"fillMode":"both","property":"transform.rotation.z","autoreverses":false,"duration":1,"to":{"scalar":-5.271816814553125e-10}}],"fillMode":"both","autoreverses":false,"duration":1}],"layers":[],"texturedRectangle":{"singleTextureOpacity":1,"textXHeight":0,"shapePath":{"lineWidth":1,"flatness":0.6,"lineCapStyle":0,"elements":[{"type":"MoveToPoint","points":[[287.9382423516514,20.85464652362555]]},{"type":"AddCurve","points":[[352.5214556188764,40.81717331681779],[352.521455635939,73.18282410760685],[287.9382423897617,93.14535096889324]]},{"type":"AddCurve","points":[[223.3550291435845,113.1078778301797],[118.6449518420873,113.1078778853809],[54.06173857486226,93.14535109218866]]},{"type":"AddCurve","points":[[-10.52147469236274,73.18282429899637],[-10.52147470942532,40.81717350820736],[54.06173853675193,20.85464664692097]]},{"type":"AddCurve","points":[[118.6449517829292,0.8921197856345202],[223.3550290844264,0.8921197304333077],[287.9382423516514,20.85464652362555]]},{"type":"CloseSubpath"},{"type":"MoveToPoint","points":[[287.9382423516514,20.85464652362555]]}],"windingRule":0,"lineJoinStyle":0,"miterLimit":10},"isBackgroundTexture":true,"textBaseline":0,"isVerticalText":false,"textureType":5},"initialState":{"affineTransform":[1,0,0,1,0,0],"masksToBounds":false,"rotation":0,"scale":1,"position":{"pointX":169.3756561279297,"pointY":55.11724472045898},"width":342,"sublayerTransform":[1,0,0,0,0,1,0,0,0,0,1,0,0,0,0,1],"contentsRect":{"y":0,"x":0,"width":1,"height":1},"opacity":1,"edgeAntialiasingMask":0,"height":114,"hidden":false,"anchorPoint":{"pointX":0.4999999553836577,"pointY":0.4999999665377433}},"texture":"2DA405A25AE2480223DCDBABEFBFEF7B"}]},{"animations":[{"timeOffset":0,"beginTime":0,"repeatCount":0,"animations":[{"timeOffset":0,"from":{"scalar":0.005},"beginTime":0,"repeatCount":0,"fillMode":"both","duration":1,"autoreverses":false,"timingFunction":"EaseInEaseOut","property":"zPosition","to":{"scalar":0.005}}],"fillMode":"both","autoreverses":false,"duration":1}],"initialState":{"affineTransform":[1,0,0,1,0,0],"masksToBounds":false,"rotation":0,"scale":1,"position":{"pointX":512.0000066757202,"pointY":676.8543448448181},"width":785.3512706756592,"sublayerTransform":[1,0,0,0,0,1,0,0,0,0,1,0,0,0,0,1],"contentsRect":{"y":0,"x":0,"width":1,"height":1},"opacity":1,"edgeAntialiasingMask":251658240,"height":176.1048078536987,"hidden":false,"anchorPoint":{"pointX":0.5,"pointY":0.5}},"layers":[{"animations":[{"timeOffset":0,"beginTime":0,"repeatCount":0,"animations":[{"timeOffset":0,"from":{"scalar":0},"beginTime":0.6667000000000001,"repeatCount":0,"fillMode":"both","duration":0.3333,"autoreverses":false,"timingFunction":"EaseInEaseOut","property":"opacity","to":{"scalar":1}},{"timeOffset":0,"from":{"scalar":false},"beginTime":0.6667000000000001,"repeatCount":0,"fillMode":"forwards","property":"hidden","autoreverses":false,"duration":0.3332999999999999,"to":{"scalar":false}}],"fillMode":"both","autoreverses":false,"duration":1}],"layers":[],"texturedRectangle":{"singleTextureOpacity":1,"textXHeight":0,"shapePath":{"lineWidth":1,"flatness":0.6,"lineCapStyle":0,"elements":[{"type":"MoveToPoint","points":[[23.32437133789062,27.80194091796875]]},{"type":"AddLine","points":[[764.6756420135498,27.80194091796875]]},{"type":"AddLine","points":[[764.6756420135498,153.9067487716675]]},{"type":"AddLine","points":[[23.32437133789062,153.9067487716675]]},{"type":"CloseSubpath"},{"type":"MoveToPoint","points":[[23.32437133789062,27.80194091796875]]}],"windingRule":0,"lineJoinStyle":0,"miterLimit":10},"isBackgroundTexture":true,"textBaseline":0,"isVerticalText":false,"textureType":5},"initialState":{"affineTransform":[1,0,0,1,0,0],"masksToBounds":false,"rotation":0,"scale":1,"position":{"pointX":392.6756286621094,"pointY":89.05240631103514},"width":788,"sublayerTransform":[1,0,0,0,0,1,0,0,0,0,1,0,0,0,0,1],"contentsRect":{"y":0,"x":0,"width":1,"height":1},"opacity":1,"edgeAntialiasingMask":0,"height":179,"hidden":true,"anchorPoint":{"pointX":0.5,"pointY":0.5075661856368933}},"texture":"372D79640346414F225CBCC917480A6A"}]},{"animations":[{"timeOffset":0,"beginTime":0,"repeatCount":0,"animations":[{"timeOffset":0,"from":{"scalar":0.006},"beginTime":0,"repeatCount":0,"fillMode":"both","duration":1,"autoreverses":false,"timingFunction":"EaseInEaseOut","property":"zPosition","to":{"scalar":0.006}}],"fillMode":"both","autoreverses":false,"duration":1}],"initialState":{"affineTransform":[1,0,0,1,0,0],"masksToBounds":false,"rotation":0,"scale":1,"position":{"pointX":512.0000066757202,"pointY":676.8543448448181},"width":785.3512706756592,"sublayerTransform":[1,0,0,0,0,1,0,0,0,0,1,0,0,0,0,1],"contentsRect":{"y":0,"x":0,"width":1,"height":1},"opacity":1,"edgeAntialiasingMask":251658240,"height":176.1048078536987,"hidden":false,"anchorPoint":{"pointX":0.5,"pointY":0.5}},"layers":[{"animations":[{"timeOffset":0,"beginTime":0,"repeatCount":0,"animations":[{"timeOffset":0,"from":{"scalar":0},"beginTime":0.6667000000000001,"repeatCount":0,"fillMode":"both","duration":0.3333,"autoreverses":false,"timingFunction":"EaseInEaseOut","property":"opacity","to":{"scalar":1}},{"timeOffset":0,"from":{"scalar":false},"beginTime":0.6667000000000001,"repeatCount":0,"fillMode":"forwards","property":"hidden","autoreverses":false,"duration":0.3332999999999999,"to":{"scalar":false}}],"fillMode":"both","autoreverses":false,"duration":1}],"layers":[],"texturedRectangle":{"singleTextureOpacity":1,"textXHeight":0.4183640252976191,"textBaseline":0.7202933175223214,"isBackgroundTexture":true,"isVerticalText":false,"textColor":[0,0.5603182911872864,0,1],"textureType":6},"initialState":{"affineTransform":[1,0,0,1,0,0],"masksToBounds":false,"rotation":0,"scale":1,"position":{"pointX":392.6756286621094,"pointY":89.05240631103516},"width":652,"sublayerTransform":[1,0,0,0,0,1,0,0,0,0,1,0,0,0,0,1],"contentsRect":{"y":0,"x":0,"width":1,"height":1},"opacity":1,"edgeAntialiasingMask":0,"height":21,"hidden":true,"anchorPoint":{"pointX":0.5199386503067485,"pointY":2.040683201381138}},"texture":"E61C829B516BE9C2D3380EFB12DD58F5"}]},{"animations":[{"timeOffset":0,"beginTime":0,"repeatCount":0,"animations":[{"timeOffset":0,"from":{"scalar":0.007},"beginTime":0,"repeatCount":0,"fillMode":"both","duration":1,"autoreverses":false,"timingFunction":"EaseInEaseOut","property":"zPosition","to":{"scalar":0.007}}],"fillMode":"both","autoreverses":false,"duration":1}],"initialState":{"affineTransform":[1,0,0,1,0,0],"masksToBounds":false,"rotation":0,"scale":1,"position":{"pointX":512.0000066757202,"pointY":676.8543448448181},"width":785.3512706756592,"sublayerTransform":[1,0,0,0,0,1,0,0,0,0,1,0,0,0,0,1],"contentsRect":{"y":0,"x":0,"width":1,"height":1},"opacity":1,"edgeAntialiasingMask":251658240,"height":176.1048078536987,"hidden":false,"anchorPoint":{"pointX":0.5,"pointY":0.5}},"layers":[{"animations":[{"timeOffset":0,"beginTime":0,"repeatCount":0,"animations":[{"timeOffset":0,"from":{"scalar":0},"beginTime":0.6667000000000001,"repeatCount":0,"fillMode":"both","duration":0.3333,"autoreverses":false,"timingFunction":"EaseInEaseOut","property":"opacity","to":{"scalar":1}},{"timeOffset":0,"from":{"scalar":false},"beginTime":0.6667000000000001,"repeatCount":0,"fillMode":"forwards","property":"hidden","autoreverses":false,"duration":0.3332999999999999,"to":{"scalar":false}}],"fillMode":"both","autoreverses":false,"duration":1}],"layers":[],"texturedRectangle":{"singleTextureOpacity":1,"textXHeight":0.4183640252976191,"textBaseline":0.7202933175223214,"isBackgroundTexture":true,"isVerticalText":false,"textColor":[0,0.5603182911872864,0,1],"textureType":6},"initialState":{"affineTransform":[1,0,0,1,0,0],"masksToBounds":false,"rotation":0,"scale":1,"position":{"pointX":392.6756286621094,"pointY":89.05240631103516},"width":638,"sublayerTransform":[1,0,0,0,0,1,0,0,0,0,1,0,0,0,0,1],"contentsRect":{"y":0,"x":0,"width":1,"height":1},"opacity":1,"edgeAntialiasingMask":0,"height":21,"hidden":true,"anchorPoint":{"pointX":0.4545454545454545,"pointY":0.9454451061430431}},"texture":"3559C8E587DE6FF7C6AFC2433E257C5B"}]},{"animations":[{"timeOffset":0,"beginTime":0,"repeatCount":0,"animations":[{"timeOffset":0,"from":{"scalar":0.008},"beginTime":0,"repeatCount":0,"fillMode":"both","duration":1,"autoreverses":false,"timingFunction":"EaseInEaseOut","property":"zPosition","to":{"scalar":0.008}}],"fillMode":"both","autoreverses":false,"duration":1}],"initialState":{"affineTransform":[1,0,0,1,0,0],"masksToBounds":false,"rotation":0,"scale":1,"position":{"pointX":512.0000066757202,"pointY":676.8543448448181},"width":785.3512706756592,"sublayerTransform":[1,0,0,0,0,1,0,0,0,0,1,0,0,0,0,1],"contentsRect":{"y":0,"x":0,"width":1,"height":1},"opacity":1,"edgeAntialiasingMask":251658240,"height":176.1048078536987,"hidden":false,"anchorPoint":{"pointX":0.5,"pointY":0.5}},"layers":[{"animations":[{"timeOffset":0,"beginTime":0,"repeatCount":0,"animations":[{"timeOffset":0,"from":{"scalar":0},"beginTime":0.6667000000000001,"repeatCount":0,"fillMode":"both","duration":0.3333,"autoreverses":false,"timingFunction":"EaseInEaseOut","property":"opacity","to":{"scalar":1}},{"timeOffset":0,"from":{"scalar":false},"beginTime":0.6667000000000001,"repeatCount":0,"fillMode":"forwards","property":"hidden","autoreverses":false,"duration":0.3332999999999999,"to":{"scalar":false}}],"fillMode":"both","autoreverses":false,"duration":1}],"layers":[],"texturedRectangle":{"singleTextureOpacity":1,"textXHeight":0.4183640252976191,"textBaseline":0.7202933175223214,"isBackgroundTexture":true,"isVerticalText":false,"textColor":[0,0.5603182911872864,0,1],"textureType":6},"initialState":{"affineTransform":[1,0,0,1,0,0],"masksToBounds":false,"rotation":0,"scale":1,"position":{"pointX":392.6756286621094,"pointY":89.05240631103516},"width":550,"sublayerTransform":[1,0,0,0,0,1,0,0,0,0,1,0,0,0,0,1],"contentsRect":{"y":0,"x":0,"width":1,"height":1},"opacity":1,"edgeAntialiasingMask":0,"height":21,"hidden":true,"anchorPoint":{"pointX":0.4472727272727273,"pointY":-0.1497929890950521}},"texture":"0481037350EC986D0C7472F6F4EA3FCB"}]},{"animations":[{"timeOffset":0,"beginTime":0,"repeatCount":0,"animations":[{"timeOffset":0,"from":{"scalar":0.009000000000000001},"beginTime":0,"repeatCount":0,"fillMode":"both","duration":1,"autoreverses":false,"timingFunction":"EaseInEaseOut","property":"zPosition","to":{"scalar":0.009000000000000001}}],"fillMode":"both","autoreverses":false,"duration":1}],"initialState":{"affineTransform":[1,0,0,1,0,0],"masksToBounds":false,"rotation":0,"scale":1,"position":{"pointX":512.0000066757202,"pointY":676.8543448448181},"width":785.3512706756592,"sublayerTransform":[1,0,0,0,0,1,0,0,0,0,1,0,0,0,0,1],"contentsRect":{"y":0,"x":0,"width":1,"height":1},"opacity":1,"edgeAntialiasingMask":251658240,"height":176.1048078536987,"hidden":false,"anchorPoint":{"pointX":0.5,"pointY":0.5}},"layers":[{"animations":[{"timeOffset":0,"beginTime":0,"repeatCount":0,"animations":[{"timeOffset":0,"from":{"scalar":0},"beginTime":0.6667000000000001,"repeatCount":0,"fillMode":"both","duration":0.3333,"autoreverses":false,"timingFunction":"EaseInEaseOut","property":"opacity","to":{"scalar":1}},{"timeOffset":0,"from":{"scalar":false},"beginTime":0.6667000000000001,"repeatCount":0,"fillMode":"forwards","property":"hidden","autoreverses":false,"duration":0.3332999999999999,"to":{"scalar":false}}],"fillMode":"both","autoreverses":false,"duration":1}],"layers":[],"texturedRectangle":{"singleTextureOpacity":1,"textXHeight":0.4183640252976191,"textBaseline":0.7202933175223214,"isBackgroundTexture":true,"isVerticalText":false,"textColor":[0.3091352581977844,0.5705211162567139,0.5744842886924744,1],"textureType":6},"initialState":{"affineTransform":[1,0,0,1,0,0],"masksToBounds":false,"rotation":0,"scale":1,"position":{"pointX":392.6756286621094,"pointY":89.05240631103516},"width":285,"sublayerTransform":[1,0,0,0,0,1,0,0,0,0,1,0,0,0,0,1],"contentsRect":{"y":0,"x":0,"width":1,"height":1},"opacity":1,"edgeAntialiasingMask":0,"height":21,"hidden":true,"anchorPoint":{"pointX":-0.01754385964912281,"pointY":-1.245031084333147}},"texture":"F6813DEC34DB90071FC3F14E41C3E19E"}]},{"animations":[{"timeOffset":0,"beginTime":0,"repeatCount":0,"animations":[{"timeOffset":0,"from":{"scalar":0.01},"beginTime":0,"repeatCount":0,"fillMode":"both","duration":1,"autoreverses":false,"timingFunction":"EaseInEaseOut","property":"zPosition","to":{"scalar":0.01}}],"fillMode":"both","autoreverses":false,"duration":1}],"initialState":{"affineTransform":[1,0,0,1,0,0],"masksToBounds":false,"rotation":0,"scale":1,"position":{"pointX":511.9999980926514,"pointY":588.0309665203094},"width":747.1241416931152,"sublayerTransform":[1,0,0,0,0,1,0,0,0,0,1,0,0,0,0,1],"contentsRect":{"y":0,"x":0,"width":1,"height":1},"opacity":1,"edgeAntialiasingMask":251658240,"height":140.1659369468689,"hidden":false,"anchorPoint":{"pointX":0.5,"pointY":0.5}},"layers":[{"animations":[{"timeOffset":0,"beginTime":0,"repeatCount":0,"animations":[{"timeOffset":0,"from":{"scalar":1},"beginTime":0,"repeatCount":0,"fillMode":"both","duration":1,"autoreverses":false,"timingFunction":"EaseInEaseOut","property":"transform.scale.x","to":{"scalar":1}},{"timeOffset":0,"from":{"scalar":1},"beginTime":0,"repeatCount":0,"fillMode":"both","duration":1,"autoreverses":false,"timingFunction":"EaseInEaseOut","property":"transform.scale.y","to":{"scalar":0.9930555555555556}},{"timeOffset":0,"from":{"texture":"43059EB58D01D0B6F8BAC866913D3768"},"beginTime":0.3333,"repeatCount":0,"fillMode":"both","duration":0.6667,"autoreverses":false,"timingFunction":"EaseInEaseOut","property":"contents","to":{"texture":"58084A932F98F87AD2CD2D550BB8C3C2"}},{"timeOffset":0,"from":{"pointX":0,"pointY":0},"beginTime":0,"repeatCount":0,"fillMode":"both","duration":1,"autoreverses":false,"timingFunction":"EaseInEaseOut","property":"transform.translation","to":{"pointX":0,"pointY":-83.50715949800281}}],"fillMode":"both","autoreverses":false,"duration":1}],"layers":[],"texturedRectangle":{"singleTextureOpacity":1,"textXHeight":0,"shapePath":{"lineWidth":1,"flatness":0.6,"lineCapStyle":0,"elements":[{"type":"MoveToPoint","points":[[23.43792724609375,27.947998046875]]},{"type":"AddLine","points":[[726.562068939209,27.947998046875]]},{"type":"AddLine","points":[[726.562068939209,118.1139349937439]]},{"type":"AddLine","points":[[23.43792724609375,118.1139349937439]]},{"type":"CloseSubpath"},{"type":"MoveToPoint","points":[[23.43792724609375,27.947998046875]]}],"windingRule":0,"lineJoinStyle":0,"miterLimit":10},"isBackgroundTexture":true,"textBaseline":0,"isVerticalText":false,"textureType":5},"initialState":{"affineTransform":[1,0,0,1,0,0],"masksToBounds":false,"rotation":0,"scale":1,"position":{"pointX":373.5620727539062,"pointY":71.08296966552734},"width":750,"sublayerTransform":[1,0,0,0,0,1,0,0,0,0,1,0,0,0,0,1],"contentsRect":{"y":0,"x":0,"width":1,"height":1},"opacity":1,"edgeAntialiasingMask":0,"height":144,"hidden":false,"anchorPoint":{"pointX":0.5,"pointY":0.507159498002794}},"texture":"43059EB58D01D0B6F8BAC866913D3768"}]}]},"effects":[],"duration":1,"type":"transition","name":"apple:magic-move-implied-motion-path","objectID":"0"}],"automaticPlay":false,"hyperlinks":[],"accessibility":[{"text":"python-nbis.png","targetRectangle":{"y":704.3445434570312,"x":949.4977416992188,"width":73.28860473632812,"height":61.73155212402344}},{"text":"open('filename', 'r', encoding='utf-8')","targetRectangle":{"y":576.947998046875,"x":277.9619140625,"width":468.076171875,"height":24}},{"text":"￼","targetRectangle":{"y":726.0103149414062,"x":980.9220289289951,"width":10.44000000000005,"height":18.39999270439148}},{"text":"I/O Files","targetRectangle":{"y":362.1327514247463,"x":435.9385478099422,"width":152.1215469843123,"height":43.60220344933629}}],"baseLayer":{"animations":[],"initialState":{"affineTransform":[1,0,0,1,0,0],"masksToBounds":false,"rotation":0,"scale":1,"position":{"pointX":512,"pointY":384},"width":1024,"sublayerTransform":[1,0,0,0,0,1,0,0,0,0,1,0,0,0,0,1],"contentsRect":{"y":0,"x":0,"width":1,"height":1},"opacity":1,"edgeAntialiasingMask":251658240,"height":768,"hidden":false,"anchorPoint":{"pointX":0.5,"pointY":0.5}},"objectID":"0","layers":[{"animations":[],"initialState":{"affineTransform":[1,0,0,1,0,0],"masksToBounds":false,"rotation":0,"scale":1,"position":{"pointX":512,"pointY":384},"width":1024,"sublayerTransform":[1,0,0,0,0,1,0,0,0,0,1,-0.0004922987690640373,0,0,0,1],"contentsRect":{"y":0,"x":0,"width":1,"height":1},"opacity":1,"edgeAntialiasingMask":251658240,"height":768,"hidden":false,"anchorPoint":{"pointX":0.5,"pointY":0.5}},"layers":[{"animations":[],"initialState":{"affineTransform":[1,0,0,1,0,0],"masksToBounds":false,"rotation":0,"scale":1,"position":{"pointX":512,"pointY":384},"width":1024,"sublayerTransform":[1,0,0,0,0,1,0,0,0,0,1,0,0,0,0,1],"contentsRect":{"y":0,"x":0,"width":1,"height":1},"opacity":1,"edgeAntialiasingMask":251658240,"height":768,"hidden":false,"anchorPoint":{"pointX":0.5,"pointY":0.5}},"layers":[{"animations":[],"layers":[],"texturedRectangle":{"isBackgroundTexture":true,"singleTextureOpacity":1,"textureType":1,"textBaseline":0,"textXHeight":0,"isVerticalText":false},"initialState":{"affineTransform":[1,0,0,1,0,0],"masksToBounds":false,"rotation":0,"scale":1,"position":{"pointX":512,"pointY":384},"width":1024,"sublayerTransform":[1,0,0,0,0,1,0,0,0,0,1,0,0,0,0,1],"contentsRect":{"y":0,"x":0,"width":1,"height":1},"opacity":1,"edgeAntialiasingMask":0,"height":768,"hidden":false,"anchorPoint":{"pointX":0.5,"pointY":0.5}},"texture":"C7A3C9712269BCFBA377590A13996216"}]}]},{"animations":[],"initialState":{"affineTransform":[1,0,0,1,0,0],"masksToBounds":false,"rotation":0,"scale":1,"position":{"pointX":986.1420440673828,"pointY":735.210319519043},"width":73.28860473632812,"sublayerTransform":[1,0,0,0,0,1,0,0,0,0,1,0,0,0,0,1],"contentsRect":{"y":0,"x":0,"width":1,"height":1},"opacity":1,"edgeAntialiasingMask":251658240,"height":61.73155212402344,"hidden":false,"anchorPoint":{"pointX":0.5,"pointY":0.5}},"layers":[{"animations":[],"layers":[],"texturedRectangle":{"isBackgroundTexture":true,"singleTextureOpacity":1,"textureType":5,"textBaseline":0,"textXHeight":0,"isVerticalText":false},"initialState":{"affineTransform":[1,0,0,1,0,0],"masksToBounds":false,"rotation":0,"scale":1,"position":{"pointX":36.64430236816407,"pointY":30.86577606201172},"width":76,"sublayerTransform":[1,0,0,0,0,1,0,0,0,0,1,0,0,0,0,1],"contentsRect":{"y":0,"x":0,"width":1,"height":1},"opacity":1,"edgeAntialiasingMask":0,"height":65,"hidden":false,"anchorPoint":{"pointX":0.501869000886616,"pointY":0.4955433772160457}},"texture":"05EBB03D9A851B3084D14365D8904CA2"}]},{"animations":[],"initialState":{"affineTransform":[1,0,0,1,0,0],"masksToBounds":false,"rotation":0,"scale":1,"position":{"pointX":986.1420244574547,"pointY":735.2103114724159},"width":29.87999618053436,"sublayerTransform":[1,0,0,0,0,1,0,0,0,0,1,0,0,0,0,1],"contentsRect":{"y":0,"x":0,"width":1,"height":1},"opacity":1,"edgeAntialiasingMask":251658240,"height":30.39999306201935,"hidden":false,"anchorPoint":{"pointX":0.5,"pointY":0.5}},"layers":[{"animations":[],"layers":[],"texturedRectangle":{"singleTextureOpacity":1,"textXHeight":0,"shapePath":{"lineWidth":1,"flatness":0.6,"lineCapStyle":0,"elements":[{"type":"MoveToPoint","points":[[31.70619841529719,10.46229085407344]]},{"type":"AddCurve","points":[[37.54063059186342,16.3982587376297],[37.54063059186342,26.02236420720214],[31.70619841529719,31.9583320907584]]},{"type":"AddCurve","points":[[25.87176623873097,37.89429997431466],[16.41228267617839,37.89429997431466],[10.57785049961217,31.9583320907584]]},{"type":"AddCurve","points":[[4.743418323045944,26.02236420720214],[4.743418323045944,16.3982587376297],[10.57785049961217,10.46229085407344]]},{"type":"AddCurve","points":[[16.41228267617839,4.526322970517185],[25.87176623873097,4.526322970517185],[31.70619841529719,10.46229085407344]]},{"type":"CloseSubpath"},{"type":"MoveToPoint","points":[[31.70619841529719,10.46229085407344]]}],"windingRule":0,"lineJoinStyle":0,"miterLimit":10},"isBackgroundTexture":true,"textBaseline":0,"isVerticalText":false,"textureType":5},"initialState":{"affineTransform":[1,0,0,1,0,0],"masksToBounds":false,"rotation":0,"scale":1,"position":{"pointX":14.93999862670898,"pointY":15.19999694824219},"width":43,"sublayerTransform":[1,0,0,0,0,1,0,0,0,0,1,0,0,0,0,1],"contentsRect":{"y":0,"x":0,"width":1,"height":1},"opacity":1,"edgeAntialiasingMask":0,"height":43,"hidden":false,"anchorPoint":{"pointX":0.4916749998580578,"pointY":0.4932630672011264}},"texture":"1834EDE3D908F36093AD2909D975FA4C"}]},{"animations":[],"initialState":{"affineTransform":[1,0,0,1,0,0],"masksToBounds":false,"rotation":0,"scale":1,"position":{"pointX":986.1420288085938,"pointY":735.2103118896484},"width":19.43999975919724,"sublayerTransform":[1,0,0,0,0,1,0,0,0,0,1,0,0,0,0,1],"contentsRect":{"y":0,"x":0,"width":1,"height":1},"opacity":1,"edgeAntialiasingMask":251658240,"height":26.39999389648438,"hidden":false,"anchorPoint":{"pointX":0.5,"pointY":0.5}},"layers":[{"animations":[],"layers":[],"texturedRectangle":{"singleTextureOpacity":1,"textXHeight":0.5931,"textBaseline":0.8382151141762734,"isBackgroundTexture":true,"isVerticalText":false,"textColor":[0.8983241319656372,0.8015710711479187,0.4699850678443909,1],"textureType":6},"initialState":{"affineTransform":[1,0,0,1,0,0],"masksToBounds":false,"rotation":0,"scale":1,"position":{"pointX":9.720000000000027,"pointY":13.19999635219574},"width":14,"sublayerTransform":[1,0,0,0,0,1,0,0,0,0,1,0,0,0,0,1],"contentsRect":{"y":0,"x":0,"width":1,"height":1},"opacity":1,"edgeAntialiasingMask":0,"height":20,"hidden":false,"anchorPoint":{"pointX":0.5101449234996542,"pointY":0.5105155646800995}},"texture":"09765695C6431BB50006402D4727B402"}]},{"animations":[],"initialState":{"affineTransform":[1,0,0,1,0,0],"masksToBounds":false,"rotation":0,"scale":1,"position":{"pointX":511.9999904632568,"pointY":383.9999988079071},"width":338.7513236999512,"sublayerTransform":[1,0,0,0,0,1,0,0,0,0,1,0,0,0,0,1],"contentsRect":{"y":0,"x":0,"width":1,"height":1},"opacity":1,"edgeAntialiasingMask":251658240,"height":110.2344946861267,"hidden":false,"anchorPoint":{"pointX":0.5,"pointY":0.5}},"layers":[{"animations":[],"layers":[],"texturedRectangle":{"singleTextureOpacity":1,"textXHeight":0,"shapePath":{"lineWidth":1,"flatness":0.6,"lineCapStyle":0,"elements":[{"type":"MoveToPoint","points":[[287.9382423516514,20.85464652362555]]},{"type":"AddCurve","points":[[352.5214556188764,40.81717331681779],[352.521455635939,73.18282410760685],[287.9382423897617,93.14535096889324]]},{"type":"AddCurve","points":[[223.3550291435845,113.1078778301797],[118.6449518420873,113.1078778853809],[54.06173857486226,93.14535109218866]]},{"type":"AddCurve","points":[[-10.52147469236274,73.18282429899637],[-10.52147470942532,40.81717350820736],[54.06173853675193,20.85464664692097]]},{"type":"AddCurve","points":[[118.6449517829292,0.8921197856345202],[223.3550290844264,0.8921197304333077],[287.9382423516514,20.85464652362555]]},{"type":"CloseSubpath"},{"type":"MoveToPoint","points":[[287.9382423516514,20.85464652362555]]}],"windingRule":0,"lineJoinStyle":0,"miterLimit":10},"isBackgroundTexture":true,"textBaseline":0,"isVerticalText":false,"textureType":5},"initialState":{"affineTransform":[1,0,0,1,0,0],"masksToBounds":false,"rotation":0,"scale":1,"position":{"pointX":169.3756561279297,"pointY":55.11724472045898},"width":342,"sublayerTransform":[1,0,0,0,0,1,0,0,0,0,1,0,0,0,0,1],"contentsRect":{"y":0,"x":0,"width":1,"height":1},"opacity":1,"edgeAntialiasingMask":0,"height":114,"hidden":false,"anchorPoint":{"pointX":0.4999999553836577,"pointY":0.4999999665377433}},"texture":"2DA405A25AE2480223DCDBABEFBFEF7B"}]},{"animations":[],"initialState":{"affineTransform":[1,0,0,1,0,0],"masksToBounds":false,"rotation":0,"scale":1,"position":{"pointX":512.0000066757202,"pointY":676.8543448448181},"width":785.3512706756592,"sublayerTransform":[1,0,0,0,0,1,0,0,0,0,1,0,0,0,0,1],"contentsRect":{"y":0,"x":0,"width":1,"height":1},"opacity":1,"edgeAntialiasingMask":251658240,"height":176.1048078536987,"hidden":false,"anchorPoint":{"pointX":0.5,"pointY":0.5}},"layers":[{"animations":[],"layers":[],"texturedRectangle":{"singleTextureOpacity":1,"textXHeight":0,"shapePath":{"lineWidth":1,"flatness":0.6,"lineCapStyle":0,"elements":[{"type":"MoveToPoint","points":[[23.32437133789062,27.80194091796875]]},{"type":"AddLine","points":[[764.6756420135498,27.80194091796875]]},{"type":"AddLine","points":[[764.6756420135498,153.9067487716675]]},{"type":"AddLine","points":[[23.32437133789062,153.9067487716675]]},{"type":"CloseSubpath"},{"type":"MoveToPoint","points":[[23.32437133789062,27.80194091796875]]}],"windingRule":0,"lineJoinStyle":0,"miterLimit":10},"isBackgroundTexture":true,"textBaseline":0,"isVerticalText":false,"textureType":5},"initialState":{"affineTransform":[1,0,0,1,0,0],"masksToBounds":false,"rotation":0,"scale":1,"position":{"pointX":392.6756286621094,"pointY":89.05240631103514},"width":788,"sublayerTransform":[1,0,0,0,0,1,0,0,0,0,1,0,0,0,0,1],"contentsRect":{"y":0,"x":0,"width":1,"height":1},"opacity":1,"edgeAntialiasingMask":0,"height":179,"hidden":true,"anchorPoint":{"pointX":0.5,"pointY":0.5075661856368933}},"texture":"372D79640346414F225CBCC917480A6A"}]},{"animations":[],"initialState":{"affineTransform":[1,0,0,1,0,0],"masksToBounds":false,"rotation":0,"scale":1,"position":{"pointX":512.0000066757202,"pointY":676.8543448448181},"width":785.3512706756592,"sublayerTransform":[1,0,0,0,0,1,0,0,0,0,1,0,0,0,0,1],"contentsRect":{"y":0,"x":0,"width":1,"height":1},"opacity":1,"edgeAntialiasingMask":251658240,"height":176.1048078536987,"hidden":false,"anchorPoint":{"pointX":0.5,"pointY":0.5}},"layers":[{"animations":[],"layers":[],"texturedRectangle":{"singleTextureOpacity":1,"textXHeight":0.4183640252976191,"textBaseline":0.7202933175223214,"isBackgroundTexture":true,"isVerticalText":false,"textColor":[0,0.5603182911872864,0,1],"textureType":6},"initialState":{"affineTransform":[1,0,0,1,0,0],"masksToBounds":false,"rotation":0,"scale":1,"position":{"pointX":392.6756286621094,"pointY":89.05240631103516},"width":652,"sublayerTransform":[1,0,0,0,0,1,0,0,0,0,1,0,0,0,0,1],"contentsRect":{"y":0,"x":0,"width":1,"height":1},"opacity":1,"edgeAntialiasingMask":0,"height":21,"hidden":true,"anchorPoint":{"pointX":0.5199386503067485,"pointY":2.040683201381138}},"texture":"E61C829B516BE9C2D3380EFB12DD58F5"}]},{"animations":[],"initialState":{"affineTransform":[1,0,0,1,0,0],"masksToBounds":false,"rotation":0,"scale":1,"position":{"pointX":512.0000066757202,"pointY":676.8543448448181},"width":785.3512706756592,"sublayerTransform":[1,0,0,0,0,1,0,0,0,0,1,0,0,0,0,1],"contentsRect":{"y":0,"x":0,"width":1,"height":1},"opacity":1,"edgeAntialiasingMask":251658240,"height":176.1048078536987,"hidden":false,"anchorPoint":{"pointX":0.5,"pointY":0.5}},"layers":[{"animations":[],"layers":[],"texturedRectangle":{"singleTextureOpacity":1,"textXHeight":0.4183640252976191,"textBaseline":0.7202933175223214,"isBackgroundTexture":true,"isVerticalText":false,"textColor":[0,0.5603182911872864,0,1],"textureType":6},"initialState":{"affineTransform":[1,0,0,1,0,0],"masksToBounds":false,"rotation":0,"scale":1,"position":{"pointX":392.6756286621094,"pointY":89.05240631103516},"width":638,"sublayerTransform":[1,0,0,0,0,1,0,0,0,0,1,0,0,0,0,1],"contentsRect":{"y":0,"x":0,"width":1,"height":1},"opacity":1,"edgeAntialiasingMask":0,"height":21,"hidden":true,"anchorPoint":{"pointX":0.4545454545454545,"pointY":0.9454451061430431}},"texture":"3559C8E587DE6FF7C6AFC2433E257C5B"}]},{"animations":[],"initialState":{"affineTransform":[1,0,0,1,0,0],"masksToBounds":false,"rotation":0,"scale":1,"position":{"pointX":512.0000066757202,"pointY":676.8543448448181},"width":785.3512706756592,"sublayerTransform":[1,0,0,0,0,1,0,0,0,0,1,0,0,0,0,1],"contentsRect":{"y":0,"x":0,"width":1,"height":1},"opacity":1,"edgeAntialiasingMask":251658240,"height":176.1048078536987,"hidden":false,"anchorPoint":{"pointX":0.5,"pointY":0.5}},"layers":[{"animations":[],"layers":[],"texturedRectangle":{"singleTextureOpacity":1,"textXHeight":0.4183640252976191,"textBaseline":0.7202933175223214,"isBackgroundTexture":true,"isVerticalText":false,"textColor":[0,0.5603182911872864,0,1],"textureType":6},"initialState":{"affineTransform":[1,0,0,1,0,0],"masksToBounds":false,"rotation":0,"scale":1,"position":{"pointX":392.6756286621094,"pointY":89.05240631103516},"width":550,"sublayerTransform":[1,0,0,0,0,1,0,0,0,0,1,0,0,0,0,1],"contentsRect":{"y":0,"x":0,"width":1,"height":1},"opacity":1,"edgeAntialiasingMask":0,"height":21,"hidden":true,"anchorPoint":{"pointX":0.4472727272727273,"pointY":-0.1497929890950521}},"texture":"0481037350EC986D0C7472F6F4EA3FCB"}]},{"animations":[],"initialState":{"affineTransform":[1,0,0,1,0,0],"masksToBounds":false,"rotation":0,"scale":1,"position":{"pointX":512.0000066757202,"pointY":676.8543448448181},"width":785.3512706756592,"sublayerTransform":[1,0,0,0,0,1,0,0,0,0,1,0,0,0,0,1],"contentsRect":{"y":0,"x":0,"width":1,"height":1},"opacity":1,"edgeAntialiasingMask":251658240,"height":176.1048078536987,"hidden":false,"anchorPoint":{"pointX":0.5,"pointY":0.5}},"layers":[{"animations":[],"layers":[],"texturedRectangle":{"singleTextureOpacity":1,"textXHeight":0.4183640252976191,"textBaseline":0.7202933175223214,"isBackgroundTexture":true,"isVerticalText":false,"textColor":[0.3091352581977844,0.5705211162567139,0.5744842886924744,1],"textureType":6},"initialState":{"affineTransform":[1,0,0,1,0,0],"masksToBounds":false,"rotation":0,"scale":1,"position":{"pointX":392.6756286621094,"pointY":89.05240631103516},"width":285,"sublayerTransform":[1,0,0,0,0,1,0,0,0,0,1,0,0,0,0,1],"contentsRect":{"y":0,"x":0,"width":1,"height":1},"opacity":1,"edgeAntialiasingMask":0,"height":21,"hidden":true,"anchorPoint":{"pointX":-0.01754385964912281,"pointY":-1.245031084333147}},"texture":"F6813DEC34DB90071FC3F14E41C3E19E"}]},{"animations":[],"initialState":{"affineTransform":[1,0,0,1,0,0],"masksToBounds":false,"rotation":0,"scale":1,"position":{"pointX":511.9999980926514,"pointY":588.0309665203094},"width":747.1241416931152,"sublayerTransform":[1,0,0,0,0,1,0,0,0,0,1,0,0,0,0,1],"contentsRect":{"y":0,"x":0,"width":1,"height":1},"opacity":1,"edgeAntialiasingMask":251658240,"height":140.1659369468689,"hidden":false,"anchorPoint":{"pointX":0.5,"pointY":0.5}},"layers":[{"animations":[],"layers":[],"texturedRectangle":{"singleTextureOpacity":1,"textXHeight":0,"shapePath":{"lineWidth":1,"flatness":0.6,"lineCapStyle":0,"elements":[{"type":"MoveToPoint","points":[[23.43792724609375,27.947998046875]]},{"type":"AddLine","points":[[726.562068939209,27.947998046875]]},{"type":"AddLine","points":[[726.562068939209,118.1139349937439]]},{"type":"AddLine","points":[[23.43792724609375,118.1139349937439]]},{"type":"CloseSubpath"},{"type":"MoveToPoint","points":[[23.43792724609375,27.947998046875]]}],"windingRule":0,"lineJoinStyle":0,"miterLimit":10},"isBackgroundTexture":true,"textBaseline":0,"isVerticalText":false,"textureType":5},"initialState":{"affineTransform":[1,0,0,1,0,0],"masksToBounds":false,"rotation":0,"scale":1,"position":{"pointX":373.5620727539062,"pointY":71.08296966552734},"width":750,"sublayerTransform":[1,0,0,0,0,1,0,0,0,0,1,0,0,0,0,1],"contentsRect":{"y":0,"x":0,"width":1,"height":1},"opacity":1,"edgeAntialiasingMask":0,"height":144,"hidden":false,"anchorPoint":{"pointX":0.5,"pointY":0.507159498002794}},"texture":"43059EB58D01D0B6F8BAC866913D3768"}]}]}}]}